{
  "changeId": "20a9f77d-37be-4da9-8cd4-328eb7118c3d",
  "sourceId": "mhlw-judo-senmon-iinkai",
  "sourceName": "柔道整復療養費検討専門委員会",
  "sourceWeight": "high",
  "targetKey": "https://www.mhlw.go.jp/stf/shingi/shingi-hosho_126707.html",
  "url": "https://www.mhlw.go.jp/stf/shingi/shingi-hosho_126707.html",
  "title": "社会保障審議会（医療保険部会 柔道整復療養費検討専門委員会）｜厚生労働省",
  "detectedAt": "2026-06-12T14:53:27.943Z",
  "changeType": "new",
  "bodyExcerpt": "ホーム > 政策について > 審議会・研究会等 > 社会保障審議会（医療保険部会 柔道整復療養費検討専門委員会） 社会保障審議会（医療保険部会 柔道整復療養費検討専門委員会） ※表を左右に動かしてご覧ください。 回数 開催日 議題等 議事録／議事要旨 資料等 開催案内 第35回 2026年4月30日（令和8年4月30日） 柔道整復療養費の令和８年度改定（案）について 議事録NEW 6月1日 資料 開催案内 第34回 2026年3月27日（令和8年3月27日） 柔道整復療養費の令和８年度改定の基本的な考え方（案）について（その３） 議事録NEW 5月19日 資料 開催案内 第33回 2026年2月27日（令和8年2月27日） 柔道整復療養費の令和８年度改定の基本的な考え方（案）について（その２） 議事録 資料 開催案内 第32回 2026年1月30日（令和8年1月30日） 柔道整復療養費の令和８年度改定の基本的な考え方（案）について 議事録 資料 開催案内 第31回 2025年3月31日（令和7年3月31日） 「柔道整復療養費のオンライン請求導入等について（中間とりまとめ）」について 議事録 資料 開催案内 第30回 2025年2月28日（令和7年2月28日） 柔道整復師の施術所におけるオンライン資格確認について 議事録 資料 開催案内 第29回 2024年4月26日（令和6年4月26日） 柔道整復療養費の令和６年料金改定（案）について 議事録 資料 開催案内 第28回 2024年3月18日（令和6年3月18日） 柔道整復療養費の令和６年改定の基本的な考え方（案）に ついて（その２） 議事録 資料 開催案内 第27回 2024年1月25日（令和6年1月25日） 柔道整復療養費の令和６年改定の基本的な考え方(案)について 議事録 資料 開催案内 第26回 2023年10月26日（令和5年10月26日） 柔道整復師の施術所におけるオンライン資格確認について 議事録 資料 開催案内 第25回 2023年9月22日（令和5年9月22日） 柔道整復師の施術所におけるオンライン資格確認について 議事録 資料 開催案内 第24回 2023年7月13日（令和5年7月13日） 柔道整復療養費のオンライン請求導入等に関するワーキング・グループにおける検討状況等の報告について 議事録 資料 開催案内 第23回 2022年7月14日（令和4年7月14日） 公的な関与の下に請求・審査・支払いが行われる仕組み、オンライン請求の導入についてのこれまでの議論及び今後の議論の進め方（案） オンライン請求の導入までの間の「療養費を施術管理者に確実に支払うための仕組み」について 議事録 資料 開催案内 第22回 2022年5月6日（令和4年5月6日） 柔道整復療養費の令和４年度料金改定（案）、明細書の義務化について 議事録 資料 開催案内 第21回 2022年3月24日（令和4年3月24日） 柔道整復療養費の令和４年改定の基本的な考え方（案）、明細書の義務化について 療養費を施術管理者に確実に支払うための仕組みについて 議事録 資料 開催案内 第20回 2022年2月24日（令和4年2月24日） 柔道整復療養費の適正化について 議事録 資料 開催案内 第19回 2022年1月31日（令和4年1月31日） 柔道整復療養費の適正化について 議事録 資料 開催案内 第18回 2021年8月6日（令和3年8月6日） 柔道整復療養費の適正化について 議事録 資料 開催案内 第17回 2020年4月22日（令和2年4月22日） 柔道整復療養費の改定について 柔道整復療養費検討専門委員会の議論の整理の各項目の状況等について 議事録 資料 開催案内 － 2020年3月31日（令和2年3月31日） － － － 開催案内 第16回 2020年2月28日（令和2年2月28日） 柔道整復療養費検討専門委員会の議論の整理の各項目の状況等について 議事録 資料 開催案内 過去の会議内容はこちら PDFファイルを見るためには、Adobe Readerというソフトが必要です。Adobe Readerは無料で配布されていますので、こちらからダウンロードしてください。 ホーム > 政策について > 審議会・研究会等 > 社会保障審議会（医療保険部会 柔道整復療養費検討専門委員会） 社会保障審議会（医療保険部会 柔道整復療養費検討専門委員会） ※表を左右に動かしてご覧ください。 回数 開催日 議題等 議事録／議事要旨 資料等 開催案内 第35回 2026年4月30日（令和8年4月30日） 柔道整復療養費の令和８年度改定（案）について 議事録NEW 6月1日 資料 開催案内 第34回 2026年3月27日（令和8年3月27日） 柔道整復療養費の令和８年度改定の基本的な考え方（案）について（その３） 議事録NEW 5月19日 資料 開催案内 第33回 2026年2月27日（令和8年2月27日） 柔道整復療養費の令和８年度改定の基本的な考え方（案）について（その２） 議事録 資料 開催案内 第32回 2026年1月30日（令和8年1月30日） 柔道整復療養費の令和８年度改定の基本的な考え方（案）について 議事録 資料 開催案内 第31回 2025年3月31日（令和7年3月31日） 「柔道整復療養費のオンライン請求導入等について（中間とりまとめ）」について 議事録 資料 開催案内 第30回 2025年2月28日（令和7年2月28日） 柔道整復師の施術所におけるオンライン資格確認について 議事録 資料 開催案内 第29回 2024年4月26日（令和6年4月26日） 柔道整復療養費の令和６年料金改定（案）について 議事録 資料 開催案内 第28回 2024年3月18日（令和6年3月18日） 柔道整復療養費の令和６年改定の基本的な考え方（案）に ついて（その２） 議事録 資料 開催案内 第27回 2024年1月25日（令和6年1月25日） 柔道整復療養費の令和６年改定の基本的な考え方(案)について 議事録 資料 開催案内 第26回 2023年10月26日（令和5年10月26日） 柔道整復師の施術所におけるオンライン資格確認について 議事録 資料 開催案内 第25回 2023年9月22日（令和5年9月22日） 柔道整復師の施術所におけるオンライン資格確認について 議事録 資料 開催案内 第24回 2023年7月13日（令和5年7月13日） 柔道整復療養費のオンライン請求導入等に関するワーキング・グループにおける検討状況等の報告について 議事録 資料 開催案内 第23回 2022年7月14日（令和4年7月14日） 公的な関与の下に請求・審査・支払いが行われる仕組み、オンライン請求の導入についてのこれまでの議論及び今後の議論の進め方（案） オンライン請求の導入までの間の「療養費を施術管理者に確実に支払うための仕組み」について 議事録 資料 開催案内 第22回 2022年5月6日（令和4年5月6日） 柔道整復療養費の令和４年度料金改定（案）、明細書の義務化について 議事録 資料 開催案内 第21回 2022年3月24日（令和4年3月24日） 柔道整復療養費の令和４年改定の基本的な考え方（案）、明細書の義務化について 療養費を施術管理者に確実に支払うための仕組みについて 議事録 資料 開催案内 第20回 2022年2月24日（令和4年2月24日） 柔道整復療養費の適正化について 議事録 資料 開催案内 第19回 2022年1月31日（令和4年1月31日） 柔道整復療養費の適正化について 議事録 資料 開催案内 第18回 2021年8月6日（令和3年8月6日） 柔道整復療養費の適正化について 議事録 資料 開催案内 第17回 2020年4月22日（令和2年4月22日） 柔道整復療養費の改定について 柔道整復療養費検討専門委員会の議論の整理の各項目の状況等について 議事録 資料 開催案内 － 2020年3月31日（令和2年3月31日） － － － 開催案内 第16回 2020年2月28日（令和2年2月28日） 柔道整復療養費検討専門委員会の議論の整理の各項目の状況等について 議事録 資料 開催案内 過去の会議内容はこちら PDFファイルを見るためには、Adobe Readerというソフトが必要です。Adobe Readerは無料で配布されていますので、こちらからダウンロードしてください。",
  "links": [
    "https://get.adobe.com/jp/reader",
    "https://www.mhlw.go.jp/index.html",
    "https://www.mhlw.go.jp/stf/newpage_09458.html",
    "https://www.mhlw.go.jp/stf/newpage_10581.html",
    "https://www.mhlw.go.jp/stf/newpage_10846.html",
    "https://www.mhlw.go.jp/stf/newpage_20206.html",
    "https://www.mhlw.go.jp/stf/newpage_23575.html",
    "https://www.mhlw.go.jp/stf/newpage_23945.html",
    "https://www.mhlw.go.jp/stf/newpage_24583.html",
    "https://www.mhlw.go.jp/stf/newpage_25410.html",
    "https://www.mhlw.go.jp/stf/newpage_26717.html",
    "https://www.mhlw.go.jp/stf/newpage_34062.html",
    "https://www.mhlw.go.jp/stf/newpage_35286.html",
    "https://www.mhlw.go.jp/stf/newpage_35793.html",
    "https://www.mhlw.go.jp/stf/newpage_37402.html",
    "https://www.mhlw.go.jp/stf/newpage_38228.html",
    "https://www.mhlw.go.jp/stf/newpage_39800.html",
    "https://www.mhlw.go.jp/stf/newpage_51984.html",
    "https://www.mhlw.go.jp/stf/newpage_54919.html",
    "https://www.mhlw.go.jp/stf/newpage_68476.html",
    "https://www.mhlw.go.jp/stf/newpage_69737.html",
    "https://www.mhlw.go.jp/stf/newpage_70468.html",
    "https://www.mhlw.go.jp/stf/newpage_70892.html",
    "https://www.mhlw.go.jp/stf/seisakunitsuite/index.html",
    "https://www.mhlw.go.jp/stf/shingi/indexshingi.html",
    "https://www.mhlw.go.jp/stf/shingi/shingi-hosho_126707_old.html",
    "https://www.mhlw.go.jp/stf/shingi2/0000195191_00004.html",
    "https://www.mhlw.go.jp/stf/shingi2/0000195191_00005.html",
    "https://www.mhlw.go.jp/stf/shingi2/0000195191_00008.html",
    "https://www.mhlw.go.jp/stf/shingi2/0000195191_00009.html",
    "https://www.mhlw.go.jp/stf/shingi2/0000195191_00010.html",
    "https://www.mhlw.go.jp/stf/shingi2/0000195191_00012.html",
    "https://www.mhlw.go.jp/stf/shingi2/0000195191_00013.html",
    "https://www.mhlw.go.jp/stf/shingi2/0000195191_00016.html",
    "https://www.mhlw.go.jp/stf/shingi2/0000195191_00017.html",
    "https://www.mhlw.go.jp/stf/shingi2/0000195191_00020.html",
    "https://www.mhlw.go.jp/stf/shingi2/0000195191_00021.html",
    "https://www.mhlw.go.jp/stf/shingi2/0000195191_00026.html",
    "https://www.mhlw.go.jp/stf/shingi2/0000195191_00028.html",
    "https://www.mhlw.go.jp/stf/shingi2/0000195191_00029.html",
    "https://www.mhlw.go.jp/stf/shingi2/0000195191_00032.html",
    "https://www.mhlw.go.jp/stf/shingi2/0000195191_00034.html",
    "https://www.mhlw.go.jp/stf/shingi2/0000204312_00003.html",
    "https://www.mhlw.go.jp/stf/shingi2/0000204312_00004.html",
    "https://www.mhlw.go.jp/stf/shingi2/0000204312_00007.html",
    "https://www.mhlw.go.jp/stf/shingi2/0000204312_00009.html",
    "https://www.mhlw.go.jp/stf/shingi2/0000204312_00011.html",
    "https://www.mhlw.go.jp/stf/shingi2/0000204312_00012.html",
    "https://www.mhlw.go.jp/stf/shingi2/0000204312_00014.html",
    "https://www.mhlw.go.jp/stf/shingi2/0000204312_00016.html",
    "https://www.mhlw.go.jp/stf/shingi2/0000204312_00017.html",
    "https://www.mhlw.go.jp/stf/shingi2/0000204312_00020.html",
    "https://www.mhlw.go.jp/stf/shingi2/0000204312_00021.html",
    "https://www.mhlw.go.jp/stf/shingi2/0000204312_00025.html",
    "https://www.mhlw.go.jp/stf/shingi2/0000204312_00027.html",
    "https://www.mhlw.go.jp/stf/shingi2/0000204312_00028.html",
    "https://www.mhlw.go.jp/stf/shingi2/0000204312_00030.html",
    "https://www.mhlw.go.jp/stf/shingi2/0000204312_00032.html",
    "https://www.mhlw.go.jp/stf/shingi2/newpage_00222.html",
    "https://www.mhlw.go.jp/stf/shingi2/newpage_00247.html",
    "https://www.mhlw.go.jp/stf/shingi2/newpage_00265.html",
    "https://www.mhlw.go.jp/stf/shingi2/newpage_00267.html",
    "https://www.mhlw.go.jp/stf/shingi2/newpage_00274.html",
    "https://www.mhlw.go.jp/stf/shingi2/newpage_71270.html",
    "https://www.mhlw.go.jp/stf/shingi2/newpage_71560.html",
    "https://www.mhlw.go.jp/stf/shingi2/newpage_72065.html"
  ],
  "httpStatus": 200,
  "pdfExcerpts": [],
  "pdfErrors": []
}
