{
  "changeId": "2fa53eb0-dd6a-4a58-b731-b2211b9e94ea",
  "sourceId": "egov-pubcomment-result-insurance",
  "sourceName": "e-Govパブコメ 結果公示（社会保険）",
  "sourceWeight": "medium",
  "targetKey": "rss:https://public-comment.e-gov.go.jp/servlet/Public?CLASSNAME=PCM1040&Mode=1&id=495260051",
  "url": "https://public-comment.e-gov.go.jp/servlet/Public?CLASSNAME=PCM1040&Mode=1&id=495260051",
  "title": "国民年金法施行令等の一部を改正する政令案に関する意見募集の結果について",
  "detectedAt": "2026-07-17T04:53:07.961Z",
  "changeType": "updated",
  "bodyExcerpt": "結果の公示日：2026/07/15 案の公示日：2026/05/15 受付締切日時：2026/06/14 00:00 命令等の公布日：2026/07/15 提出意見数：2 カテゴリー：社会保険 問合せ先（所管省庁・部局名等）：厚生労働省年金局年金課\n厚生労働省社会・援護局障害保健福祉部企画課",
  "diffText": "===================================================================\n--- previous\n+++ current\n@@ -1,5 +1,5 @@\n 国民年金法施行令等の一部を改正する政令案に関する意見募集の結果について\n-結果の公示日：2026/07/15 案の公示日：2026/05/15 受付締切日時：2026/06/14 00:00 命令等の公布日：2026/07/15 提出意見数：2 カテゴリー：社会福祉 問合せ先（所管省庁・部局名等）：厚生労働省年金局年金課\n+結果の公示日：2026/07/15 案の公示日：2026/05/15 受付締切日時：2026/06/14 00:00 命令等の公布日：2026/07/15 提出意見数：2 カテゴリー：社会保険 問合せ先（所管省庁・部局名等）：厚生労働省年金局年金課\n 厚生労働省社会・援護局障害保健福祉部企画課\n \n \n",
  "links": [],
  "httpStatus": 200
}
