{
  "changeId": "91990312-b337-4342-9c83-838db3791759",
  "sourceId": "egov-law-api",
  "sourceName": "e-Gov法令API（更新法令一覧）",
  "sourceWeight": "medium",
  "targetKey": "api:egov-law-api:429M60200000001",
  "url": "https://laws.e-gov.go.jp/api/1/updatelawlists/20260526#429M60200000001",
  "title": "公正取引委員会の確約手続に関する規則",
  "detectedAt": "2026-05-26T13:34:57.316Z",
  "changeType": "new",
  "bodyExcerpt": "{\"LawTypeName\":\"規則\",\"LawNo\":\"平成二十九年公正取引委員会規則第一号\",\"LawName\":\"公正取引委員会の確約手続に関する規則\",\"LawNameKana\":\"こうせいとりひきいいんかいのかくやくてつづきにかんするきそく\",\"OldLawName\":\"\",\"PromulgationDate\":20170125,\"AmendName\":\"公正取引委員会の審査に関する規則等の一部を改正する規則\",\"AmendNo\":\"令和八年公正取引委員会規則第二号\",\"AmendPromulgationDate\":20260501,\"EnforcementDate\":20260521,\"EnforcementComment\":\"\",\"LawId\":\"429M60200000001\",\"LawUrl\":\"https://elaws.e-gov.go.jp/document?lawid=429M60200000001_20260521_508M60200000002\",\"EnforcementFlg\":1,\"AuthFlg\":0}",
  "links": [],
  "httpStatus": 200
}
